point2d/__init__.py
point2d/point2d.py
point2d-0.0.1.dist-info/LICENSE
point2d-0.0.1.dist-info/METADATA
point2d-0.0.1.dist-info/WHEEL
point2d-0.0.1.dist-info/top_level.txt
point2d-0.0.1.dist-info/RECORD
