Metadata-Version: 2.1
Name: point2d
Version: 0.0.1
Summary: 2D point class to represent cartesian and polar coordinates seemlessly.
Home-page: https://github.com/SplinterDev/point2d
Author: Fabricio J.C. Montenegro
Author-email: fabriciojcmontenegro@gmail.com
License: UNKNOWN
Platform: UNKNOWN
Classifier: Programming Language :: Python :: 3
Classifier: License :: OSI Approved :: GNU General Public License v3 (GPLv3)
Classifier: Operating System :: OS Independent
Classifier: Topic :: Scientific/Engineering :: Mathematics
